konst/__init__.py
konst/_common.py
konst/string.py
konst/symbol.py
konst-1.0.1.dist-info/METADATA
konst-1.0.1.dist-info/WHEEL
konst-1.0.1.dist-info/top_level.txt
konst-1.0.1.dist-info/RECORD
