Metadata-Version: 2.1
Name: konst
Version: 1.0.1
Summary: Effortless, meaningless, DRY constants
Home-page: https://github.com/yehonatanz/konst
License: UNKNOWN
Platform: UNKNOWN
Classifier: License :: OSI Approved :: MIT License
Classifier: Programming Language :: Python :: 3.6
Classifier: Programming Language :: Python :: 3.7
Requires-Python: >=3.6
Provides-Extra: dev
Requires-Dist: isort; extra == 'dev'
Requires-Dist: black; extra == 'dev'
Requires-Dist: pytest; extra == 'dev'
Requires-Dist: pytest-watch; extra == 'dev'
Requires-Dist: pytest-cov; extra == 'dev'
